<?xml version="1.0"?>
<extension key="com.proveg.mods" type="module">
  <file>mods</file>
  <name>CiviCRM Modifications</name>
  <description>Adjustments for proVeg Germany</description>
  <license>AGPL-3.0</license>
  <maintainer>
    <author>SYSTOPIA</author>
    <email>endres@systopia.de</email>
  </maintainer>
  <urls>
    <url desc="Main Extension Page">https://github.com/systopia/com.proveg.mods</url>
    <url desc="Documentation">https://github.com/systopia/com.proveg.mods</url>
    <url desc="Support">https://github.com/systopia/com.proveg.mods/issues</url>
    <url desc="Licensing">http://www.gnu.org/licenses/agpl-3.0.html</url>
  </urls>
  <releaseDate>2018-10-02</releaseDate>
  <version>1.3.dev</version>
  <develStage>test</develStage>
  <compatibility>
    <ver>5</ver>
  </compatibility>
  <comments></comments>
  <civix>
    <namespace>CRM/Mods</namespace>
  </civix>
</extension>
